{"type":"FeatureCollection","features":[{"geometry":{"type":"Polygon","coordinates":[[[28.37323,51.28941],[28.37323,51.24981],[28.30078,51.24981],[28.30078,51.28941],[28.37323,51.28941]]]},"type":"Feature","id":"8d897b0c9d","clipped":true,"properties":{"gid":41,"name":"M-35-33-\u0411-\u0430"}},{"geometry":{"type":"Polygon","coordinates":[[[28.38867,51.24981],[28.37323,51.24981],[28.37323,51.28941],[28.38867,51.28941],[28.38867,51.24981]]]},"type":"Feature","id":"c1762517a8","clipped":true,"properties":{"gid":42,"name":"M-35-33-\u0411-\u0431"}},{"geometry":{"type":"Polygon","coordinates":[[[28.30078,51.24981],[28.37323,51.24981],[28.37323,51.23441],[28.30078,51.23441],[28.30078,51.24981]]]},"type":"Feature","id":"f17db49923","clipped":true,"properties":{"gid":43,"name":"M-35-33-\u0411-\u0432"}},{"geometry":{"type":"Polygon","coordinates":[[[28.37323,51.24981],[28.38867,51.24981],[28.38867,51.23441],[28.37323,51.23441],[28.37323,51.24981]]]},"type":"Feature","id":"4758ccceeb","clipped":true,"properties":{"gid":44,"name":"M-35-33-\u0411-\u0433"}}]}