{"type":"FeatureCollection","features":[{"geometry":{"type":"Polygon","coordinates":[[[28.62323,51.23441],[28.62323,51.17934],[28.56445,51.17934],[28.56445,51.23441],[28.62323,51.23441]]]},"type":"Feature","id":"fedee66cf0","clipped":true,"properties":{"gid":55,"name":"M-35-34-\u0410-\u0432"}},{"geometry":{"type":"Polygon","coordinates":[[[28.62323,51.17934],[28.62323,51.23441],[28.65234,51.23441],[28.65234,51.17934],[28.62323,51.17934]]]},"type":"Feature","id":"7a0d7e2d81","clipped":true,"properties":{"gid":56,"name":"M-35-34-\u0410-\u0433"}}]}